fedora_planet_messages/__init__.py
fedora_planet_messages/build.py
fedora_planet_messages/post_messages.py
fedora_planet_messages-1.2.0.dist-info/licenses/LICENSE
fedora_planet_messages-1.2.0.dist-info/METADATA
fedora_planet_messages-1.2.0.dist-info/WHEEL
fedora_planet_messages-1.2.0.dist-info/entry_points.txt
fedora_planet_messages-1.2.0.dist-info/top_level.txt
fedora_planet_messages-1.2.0.dist-info/RECORD
